CryptoPrice/__about__.py
CryptoPrice/__init__.py
CryptoPrice/exceptions.py
CryptoPrice/common/__init__.py
CryptoPrice/common/prices.py
CryptoPrice/common/trade.py
CryptoPrice/retrievers/AbstractRetriever.py
CryptoPrice/retrievers/BinanceRetriever.py
CryptoPrice/retrievers/KlineRetriever.py
CryptoPrice/retrievers/KucoinRetriever.py
CryptoPrice/retrievers/MetaRetriever.py
CryptoPrice/retrievers/__init__.py
CryptoPrice/storage/DataBase.py
CryptoPrice/storage/KlineDataBase.py
CryptoPrice/storage/__init__.py
CryptoPrice/storage/tables.py
CryptoPrice/utils/LoggerGenerator.py
CryptoPrice/utils/__init__.py
CryptoPrice/utils/paths.py
CryptoPrice/utils/time.py
python_CryptoPrice-0.2.0.dev0.dist-info/LICENSE
python_CryptoPrice-0.2.0.dev0.dist-info/METADATA
python_CryptoPrice-0.2.0.dev0.dist-info/WHEEL
python_CryptoPrice-0.2.0.dev0.dist-info/top_level.txt
python_CryptoPrice-0.2.0.dev0.dist-info/RECORD
