Metadata-Version: 2.1
Name: python-CryptoPrice
Version: 0.2.0.dev0
Summary: Library to retrieve price or candle history of crypto assets using multiple sources
Home-page: https://github.com/EtWnn/CryptoPrice
Author: EtWnn
Author-email: 
License: MIT
Keywords: eth bsc price ohlc candle history API Binance Kucoin
Platform: UNKNOWN
Classifier: Intended Audience :: Developers
Classifier: License :: OSI Approved :: MIT License
Classifier: Operating System :: OS Independent
Classifier: Programming Language :: Python :: 3.7
Classifier: Programming Language :: Python
Classifier: Topic :: Software Development :: Libraries :: Python Modules
License-File: LICENSE
Requires-Dist: requests
Requires-Dist: appdirs
Requires-Dist: python-binance
Requires-Dist: kucoin-python
